balsam/__init__.py
balsam/analytics.py
balsam/api.py
balsam/py.typed
balsam/querytest.py
balsam/_api/__init__.py
balsam/_api/app.py
balsam/_api/bases.py
balsam/_api/manager.py
balsam/_api/model.py
balsam/_api/models.py
balsam/_api/query.py
balsam/client/__init__.py
balsam/client/encoders.py
balsam/client/requests_client.py
balsam/client/requests_oauth.py
balsam/client/requests_password.py
balsam/client/rest_base_client.py
balsam/client/urls.py
balsam/cmdline/__init__.py
balsam/cmdline/_launcher.py
balsam/cmdline/app.py
balsam/cmdline/job.py
balsam/cmdline/launcher.py
balsam/cmdline/login.py
balsam/cmdline/scheduler.py
balsam/cmdline/server.py
balsam/cmdline/site.py
balsam/cmdline/utils.py
balsam/config/__init__.py
balsam/config/config.py
balsam/config/site_builder.py
balsam/config/defaults/settings.yml.j2
balsam/config/defaults/validate.py
balsam/config/defaults/alcf_aurora/job-template.sh
balsam/config/defaults/alcf_aurora/settings.yml
balsam/config/defaults/alcf_cooley/job-template.sh
balsam/config/defaults/alcf_cooley/settings.yml
balsam/config/defaults/alcf_polaris/job-template.sh
balsam/config/defaults/alcf_polaris/settings.yml
balsam/config/defaults/alcf_sunspot/job-template.sh
balsam/config/defaults/alcf_sunspot/settings.yml
balsam/config/defaults/alcf_theta/job-template.sh
balsam/config/defaults/alcf_theta/settings.yml
balsam/config/defaults/alcf_thetagpu/job-template.sh
balsam/config/defaults/alcf_thetagpu/settings.yml
balsam/config/defaults/nersc_perlmuttercpu/job-template.sh
balsam/config/defaults/nersc_perlmuttercpu/settings.yml
balsam/config/defaults/nersc_perlmuttergpu/job-template.sh
balsam/config/defaults/nersc_perlmuttergpu/settings.yml
balsam/config/defaults/olcf_summit/job-template.sh
balsam/config/defaults/olcf_summit/settings.yml
balsam/config/defaults/osx/job-template.sh
balsam/config/defaults/osx/settings.yml
balsam/platform/__init__.py
balsam/platform/app_run/__init__.py
balsam/platform/app_run/app_run.py
balsam/platform/app_run/aurora.py
balsam-0.7.0a24.dist-info/METADATA
balsam-0.7.0a24.dist-info/WHEEL
balsam-0.7.0a24.dist-info/entry_points.txt
balsam-0.7.0a24.dist-info/top_level.txt
balsam-0.7.0a24.dist-info/RECORD
